<?xml version="1.0" encoding="UTF-8" standalone="yes"?><aggiornamentoOri><daInserire xmlns:xsi="http://www.w3.org/2001/XMLSchema-instance" xsi:type="figuraOri"><abilitato>false</abilitato><codice>8982be4fd5551aaf</codice><dtAbilitato>2021-03-11T18:49:43+01:00</dtAbilitato><idFigura>81</idFigura><idFiguraTipo><abilitato>true</abilitato><dtAbilitato>2018-05-07T11:03:01+02:00</dtAbilitato><figura>INEPHOS OPERATOR</figura><idFiguraTipo>1</idFiguraTipo></idFiguraTipo><nominativo>Operatore  Prova</nominativo></daInserire><daInserire xmlns:xsi="http://www.w3.org/2001/XMLSchema-instance" xsi:type="figuraOri"><abilitato>false</abilitato><codice>fde9d9cfa73f1f58</codice><dtAbilitato>2021-03-11T18:49:47+01:00</dtAbilitato><idFigura>82</idFigura><idFiguraTipo><abilitato>true</abilitato><dtAbilitato>2015-06-12T12:39:38+02:00</dtAbilitato><figura>SUPPLIER</figura><idFiguraTipo>2</idFiguraTipo></idFiguraTipo><nominativo>Fornitore Prova</nominativo></daInserire><daInserire xmlns:xsi="http://www.w3.org/2001/XMLSchema-instance" xsi:type="figuraOri"><abilitato>false</abilitato><codice>1c6211de2fcc6169</codice><dtAbilitato>2021-03-11T18:54:32+01:00</dtAbilitato><idFigura>83</idFigura><idFiguraTipo><abilitato>true</abilitato><dtAbilitato>2018-05-07T10:57:00+02:00</dtAbilitato><figura>MACHINE OPERATOR</figura><idFiguraTipo>6</idFiguraTipo></idFiguraTipo><nominativo>FRANCO ZENI</nominativo></daInserire><daInserire xmlns:xsi="http://www.w3.org/2001/XMLSchema-instance" xsi:type="figuraOri"><abilitato>false</abilitato><codice>929fb9cef6ce8b60</codice><dtAbilitato>2021-03-11T18:50:36+01:00</dtAbilitato><idFigura>84</idFigura><idFiguraTipo><abilitato>true</abilitato><dtAbilitato>2018-05-07T10:57:00+02:00</dtAbilitato><figura>MACHINE OPERATOR</figura><idFiguraTipo>6</idFiguraTipo></idFiguraTipo><nominativo>FRANCO ZENI</nominativo></daInserire><daInserire xmlns:xsi="http://www.w3.org/2001/XMLSchema-instance" xsi:type="figuraOri"><abilitato>false</abilitato><codice>b749d038bbec3726</codice><dtAbilitato>2021-03-11T18:59:21+01:00</dtAbilitato><idFigura>85</idFigura><idFiguraTipo><abilitato>true</abilitato><dtAbilitato>2018-05-07T10:57:00+02:00</dtAbilitato><figura>MACHINE OPERATOR</figura><idFiguraTipo>6</idFiguraTipo></idFiguraTipo><nominativo>FRANCO ZENI</nominativo></daInserire><daInserire xmlns:xsi="http://www.w3.org/2001/XMLSchema-instance" xsi:type="figuraOri"><abilitato>false</abilitato><codice>a91dafd24cebec20</codice><dtAbilitato>2021-03-11T18:59:17+01:00</dtAbilitato><idFigura>86</idFigura><idFiguraTipo><abilitato>true</abilitato><dtAbilitato>2018-05-07T10:57:00+02:00</dtAbilitato><figura>MACHINE OPERATOR</figura><idFiguraTipo>6</idFiguraTipo></idFiguraTipo><nominativo>FRANCO ZENI</nominativo></daInserire><daInserire xmlns:xsi="http://www.w3.org/2001/XMLSchema-instance" xsi:type="figuraOri"><abilitato>true</abilitato><codice>6ed822179e41029a</codice><dtAbilitato>2021-03-11T18:59:12+01:00</dtAbilitato><idFigura>87</idFigura><idFiguraTipo><abilitato>true</abilitato><dtAbilitato>2018-05-07T10:57:00+02:00</dtAbilitato><figura>MACHINE OPERATOR</figura><idFiguraTipo>6</idFiguraTipo></idFiguraTipo><nominativo>FRANCO ZENI</nominativo></daInserire><daInserire xmlns:xsi="http://www.w3.org/2001/XMLSchema-instance" xsi:type="figuraOri"><abilitato>true</abilitato><codice>d3e1238146e1bb52</codice><dtAbilitato>2021-03-11T19:02:14+01:00</dtAbilitato><idFigura>89</idFigura><idFiguraTipo><abilitato>true</abilitato><dtAbilitato>2013-05-03T13:35:00+02:00</dtAbilitato><figura>PRODUCTION MANAGER</figura><idFiguraTipo>4</idFiguraTipo></idFiguraTipo><nominativo>HOLCIM SRL</nominativo></daInserire><tipo>IN</tipo><versione>93</versione></aggiornamentoOri>